tcontrol/__init__.py
tcontrol/canonical.py
tcontrol/discretization.py
tcontrol/exception.py
tcontrol/frequency.py
tcontrol/fsf.py
tcontrol/lti.py
tcontrol/lyapunov.py
tcontrol/model_conversion.py
tcontrol/plot_utility.py
tcontrol/poly.py
tcontrol/pzmap.py
tcontrol/rlocus.py
tcontrol/statespace.py
tcontrol/tcconfig.py
tcontrol/time_response.py
tcontrol/transferfunction.py
tcontrol/tests/__init__.py
tcontrol/tests/data_generator.py
tcontrol/tests/test.py
tcontrol/tests/test_canonical.py
tcontrol/tests/test_discretization.py
tcontrol/tests/test_frequency.py
tcontrol/tests/test_fsf.py
tcontrol/tests/test_lyapunov.py
tcontrol/tests/test_model_conv.py
tcontrol/tests/test_poly.py
tcontrol/tests/test_pzmap.py
tcontrol/tests/test_rlocus.py
tcontrol/tests/test_statespace.py
tcontrol/tests/test_time_response.py
tcontrol/tests/test_transferfunction.py
tcontrol/tests/tools/__init__.py
tcontrol/tests/tools/test_utility.py
TControl-0.9.14.dist-info/METADATA
TControl-0.9.14.dist-info/WHEEL
TControl-0.9.14.dist-info/top_level.txt
TControl-0.9.14.dist-info/RECORD
