Metadata-Version: 2.1
Name: TControl
Version: 0.9.14
Summary: 用于自动控制系统分析的Python库。
Home-page: https://gitee.com/ljcloud/TControl
Author: HOUXIN LUO
Author-email: 2577229471@qq.com
License: BSD 3-clause
Platform: UNKNOWN
Requires-Dist: sympy (>=1.0)
Requires-Dist: numpy (>=1.12.0)
Requires-Dist: matplotlib (>=2.0.0)
Requires-Dist: scipy (>=1.1.0)
